bmhub/__init__.py
bmhub/cli.py
bmhub/schema.py
bmhub/utils.py
bmhub/backend/hf.py
bmhub/backend/ms.py
bmhub/backend/schema.py
bigmodel_hub-1.0.0.dist-info/entry_points.txt
bigmodel_hub-1.0.0.dist-info/LICENSE
bigmodel_hub-1.0.0.dist-info/WHEEL
bigmodel_hub-1.0.0.dist-info/METADATA
bigmodel_hub-1.0.0.dist-info/RECORD
