Metadata-Version: 2.3
Name: bigmodel-hub
Version: 1.0.0
Summary: BigModel Hub CLI Toolkit
Keywords: Big Model,LLM,Hugging Face,ModelScope
Author-email: Shihong Yan <yansh97@foxmail.com>
Requires-Python: >=3.11,<4
Requires-Dist: setuptools
Requires-Dist: pydantic
Requires-Dist: huggingface_hub
Requires-Dist: modelscope
Requires-Dist: typer
Requires-Dist: rich
Requires-Dist: huggingface_hub[cli] ; extra == "cli"
Project-URL: Homepage, https://github.com/yansh97/bigmodel-hub
Provides-Extra: cli
